[{"DI_MONTH_NAME":"\u0e21\u0e01\u0e23\u0e32\u0e04\u0e21","TRD_QTY":"2.00","TRD_AMOUNT_PRICE":"1960.00"},{"DI_MONTH_NAME":"\u0e21\u0e01\u0e23\u0e32\u0e04\u0e21","TRD_QTY":"4043.00","TRD_AMOUNT_PRICE":"5971611.15"},{"DI_MONTH_NAME":"\u0e21\u0e01\u0e23\u0e32\u0e04\u0e21","TRD_QTY":"162.00","TRD_AMOUNT_PRICE":"281750.00"},{"DI_MONTH_NAME":"\u0e21\u0e01\u0e23\u0e32\u0e04\u0e21","TRD_QTY":"356.00","TRD_AMOUNT_PRICE":"531055.55"},{"DI_MONTH_NAME":"\u0e21\u0e01\u0e23\u0e32\u0e04\u0e21","TRD_QTY":"1.00","TRD_AMOUNT_PRICE":"3550.00"},{"DI_MONTH_NAME":"\u0e21\u0e01\u0e23\u0e32\u0e04\u0e21","TRD_QTY":"67.00","TRD_AMOUNT_PRICE":"117670.00"},{"DI_MONTH_NAME":"\u0e21\u0e01\u0e23\u0e32\u0e04\u0e21","TRD_QTY":"191.00","TRD_AMOUNT_PRICE":"274080.00"},{"DI_MONTH_NAME":"\u0e21\u0e01\u0e23\u0e32\u0e04\u0e21","TRD_QTY":"756.00","TRD_AMOUNT_PRICE":"975420.00"},{"DI_MONTH_NAME":"\u0e21\u0e01\u0e23\u0e32\u0e04\u0e21","TRD_QTY":"302.00","TRD_AMOUNT_PRICE":"476038.00"},{"DI_MONTH_NAME":"\u0e21\u0e01\u0e23\u0e32\u0e04\u0e21","TRD_QTY":"25.00","TRD_AMOUNT_PRICE":"34980.00"},{"DI_MONTH_NAME":"\u0e21\u0e01\u0e23\u0e32\u0e04\u0e21","TRD_QTY":"45.00","TRD_AMOUNT_PRICE":"80887.00"},{"DI_MONTH_NAME":"\u0e21\u0e01\u0e23\u0e32\u0e04\u0e21","TRD_QTY":"81.00","TRD_AMOUNT_PRICE":"98770.50"},{"DI_MONTH_NAME":"\u0e21\u0e01\u0e23\u0e32\u0e04\u0e21","TRD_QTY":"100.00","TRD_AMOUNT_PRICE":"172020.00"},{"DI_MONTH_NAME":"\u0e21\u0e01\u0e23\u0e32\u0e04\u0e21","TRD_QTY":"342.00","TRD_AMOUNT_PRICE":"557890.00"},{"DI_MONTH_NAME":"\u0e21\u0e01\u0e23\u0e32\u0e04\u0e21","TRD_QTY":"1980.00","TRD_AMOUNT_PRICE":"3062336.80"},{"DI_MONTH_NAME":"\u0e21\u0e01\u0e23\u0e32\u0e04\u0e21","TRD_QTY":"389.00","TRD_AMOUNT_PRICE":"590339.50"},{"DI_MONTH_NAME":"\u0e21\u0e01\u0e23\u0e32\u0e04\u0e21","TRD_QTY":"10.00","TRD_AMOUNT_PRICE":"13900.00"},{"DI_MONTH_NAME":"\u0e21\u0e01\u0e23\u0e32\u0e04\u0e21","TRD_QTY":"4975.00","TRD_AMOUNT_PRICE":"7196341.60"},{"DI_MONTH_NAME":"\u0e21\u0e01\u0e23\u0e32\u0e04\u0e21","TRD_QTY":"6.00","TRD_AMOUNT_PRICE":"14538.60"},{"DI_MONTH_NAME":"\u0e21\u0e01\u0e23\u0e32\u0e04\u0e21","TRD_QTY":"98.00","TRD_AMOUNT_PRICE":"226010.00"},{"DI_MONTH_NAME":"\u0e21\u0e01\u0e23\u0e32\u0e04\u0e21","TRD_QTY":"1991.00","TRD_AMOUNT_PRICE":"2963717.00"},{"DI_MONTH_NAME":"\u0e21\u0e01\u0e23\u0e32\u0e04\u0e21","TRD_QTY":"495.00","TRD_AMOUNT_PRICE":"833480.00"},{"DI_MONTH_NAME":"\u0e21\u0e01\u0e23\u0e32\u0e04\u0e21","TRD_QTY":"501.00","TRD_AMOUNT_PRICE":"768170.00"},{"DI_MONTH_NAME":"\u0e21\u0e01\u0e23\u0e32\u0e04\u0e21","TRD_QTY":"164.00","TRD_AMOUNT_PRICE":"322390.00"},{"DI_MONTH_NAME":"\u0e21\u0e01\u0e23\u0e32\u0e04\u0e21","TRD_QTY":"64.00","TRD_AMOUNT_PRICE":"114400.00"},{"DI_MONTH_NAME":"\u0e21\u0e01\u0e23\u0e32\u0e04\u0e21","TRD_QTY":"20.00","TRD_AMOUNT_PRICE":"25400.00"},{"DI_MONTH_NAME":"\u0e21\u0e01\u0e23\u0e32\u0e04\u0e21","TRD_QTY":"127.00","TRD_AMOUNT_PRICE":"200312.00"},{"DI_MONTH_NAME":"\u0e21\u0e01\u0e23\u0e32\u0e04\u0e21","TRD_QTY":"4.00","TRD_AMOUNT_PRICE":"7348.12"},{"DI_MONTH_NAME":"\u0e21\u0e01\u0e23\u0e32\u0e04\u0e21","TRD_QTY":"4.00","TRD_AMOUNT_PRICE":"7584.50"},{"DI_MONTH_NAME":"\u0e21\u0e01\u0e23\u0e32\u0e04\u0e21","TRD_QTY":"309.00","TRD_AMOUNT_PRICE":"479380.00"},{"DI_MONTH_NAME":"\u0e21\u0e01\u0e23\u0e32\u0e04\u0e21","TRD_QTY":"42.00","TRD_AMOUNT_PRICE":"49320.00"},{"DI_MONTH_NAME":"\u0e21\u0e01\u0e23\u0e32\u0e04\u0e21","TRD_QTY":"20.00","TRD_AMOUNT_PRICE":"19900.00"},{"DI_MONTH_NAME":"\u0e21\u0e01\u0e23\u0e32\u0e04\u0e21","TRD_QTY":"688.00","TRD_AMOUNT_PRICE":"1193500.00"},{"DI_MONTH_NAME":"\u0e21\u0e01\u0e23\u0e32\u0e04\u0e21","TRD_QTY":"809.00","TRD_AMOUNT_PRICE":"1160760.00"},{"DI_MONTH_NAME":"\u0e21\u0e01\u0e23\u0e32\u0e04\u0e21","TRD_QTY":"244.00","TRD_AMOUNT_PRICE":"392616.25"},{"DI_MONTH_NAME":"\u0e21\u0e01\u0e23\u0e32\u0e04\u0e21","TRD_QTY":"487.00","TRD_AMOUNT_PRICE":"1129750.00"},{"DI_MONTH_NAME":"\u0e21\u0e01\u0e23\u0e32\u0e04\u0e21","TRD_QTY":"174.00","TRD_AMOUNT_PRICE":"269218.00"},{"DI_MONTH_NAME":"\u0e21\u0e01\u0e23\u0e32\u0e04\u0e21","TRD_QTY":"658.00","TRD_AMOUNT_PRICE":"1085200.00"},{"DI_MONTH_NAME":"\u0e21\u0e01\u0e23\u0e32\u0e04\u0e21","TRD_QTY":"69.00","TRD_AMOUNT_PRICE":"124270.00"},{"DI_MONTH_NAME":"\u0e21\u0e01\u0e23\u0e32\u0e04\u0e21","TRD_QTY":"42.00","TRD_AMOUNT_PRICE":"64400.00"},{"DI_MONTH_NAME":"\u0e21\u0e01\u0e23\u0e32\u0e04\u0e21","TRD_QTY":"4.00","TRD_AMOUNT_PRICE":"4200.00"},{"DI_MONTH_NAME":"\u0e21\u0e01\u0e23\u0e32\u0e04\u0e21","TRD_QTY":"16.00","TRD_AMOUNT_PRICE":"30340.00"},{"DI_MONTH_NAME":"\u0e21\u0e01\u0e23\u0e32\u0e04\u0e21","TRD_QTY":"41.00","TRD_AMOUNT_PRICE":"59150.00"},{"DI_MONTH_NAME":"\u0e21\u0e01\u0e23\u0e32\u0e04\u0e21","TRD_QTY":"15.00","TRD_AMOUNT_PRICE":"18366.20"},{"DI_MONTH_NAME":"\u0e21\u0e01\u0e23\u0e32\u0e04\u0e21","TRD_QTY":"36.00","TRD_AMOUNT_PRICE":"57960.00"},{"DI_MONTH_NAME":"\u0e21\u0e01\u0e23\u0e32\u0e04\u0e21","TRD_QTY":"76.00","TRD_AMOUNT_PRICE":"110720.00"},{"DI_MONTH_NAME":"\u0e21\u0e01\u0e23\u0e32\u0e04\u0e21","TRD_QTY":"216.00","TRD_AMOUNT_PRICE":"409740.00"},{"DI_MONTH_NAME":"\u0e01\u0e38\u0e21\u0e20\u0e32\u0e1e\u0e31\u0e19\u0e18\u0e4c","TRD_QTY":"8.00","TRD_AMOUNT_PRICE":"10000.00"},{"DI_MONTH_NAME":"\u0e01\u0e38\u0e21\u0e20\u0e32\u0e1e\u0e31\u0e19\u0e18\u0e4c","TRD_QTY":"3283.00","TRD_AMOUNT_PRICE":"5159161.99"},{"DI_MONTH_NAME":"\u0e01\u0e38\u0e21\u0e20\u0e32\u0e1e\u0e31\u0e19\u0e18\u0e4c","TRD_QTY":"274.00","TRD_AMOUNT_PRICE":"452570.00"},{"DI_MONTH_NAME":"\u0e01\u0e38\u0e21\u0e20\u0e32\u0e1e\u0e31\u0e19\u0e18\u0e4c","TRD_QTY":"283.00","TRD_AMOUNT_PRICE":"374610.00"},{"DI_MONTH_NAME":"\u0e01\u0e38\u0e21\u0e20\u0e32\u0e1e\u0e31\u0e19\u0e18\u0e4c","TRD_QTY":"68.00","TRD_AMOUNT_PRICE":"108360.00"},{"DI_MONTH_NAME":"\u0e01\u0e38\u0e21\u0e20\u0e32\u0e1e\u0e31\u0e19\u0e18\u0e4c","TRD_QTY":"140.00","TRD_AMOUNT_PRICE":"168960.00"},{"DI_MONTH_NAME":"\u0e01\u0e38\u0e21\u0e20\u0e32\u0e1e\u0e31\u0e19\u0e18\u0e4c","TRD_QTY":"718.00","TRD_AMOUNT_PRICE":"1048702.30"},{"DI_MONTH_NAME":"\u0e01\u0e38\u0e21\u0e20\u0e32\u0e1e\u0e31\u0e19\u0e18\u0e4c","TRD_QTY":"231.00","TRD_AMOUNT_PRICE":"365080.00"},{"DI_MONTH_NAME":"\u0e01\u0e38\u0e21\u0e20\u0e32\u0e1e\u0e31\u0e19\u0e18\u0e4c","TRD_QTY":"30.00","TRD_AMOUNT_PRICE":"42500.00"},{"DI_MONTH_NAME":"\u0e01\u0e38\u0e21\u0e20\u0e32\u0e1e\u0e31\u0e19\u0e18\u0e4c","TRD_QTY":"182.00","TRD_AMOUNT_PRICE":"525214.74"},{"DI_MONTH_NAME":"\u0e01\u0e38\u0e21\u0e20\u0e32\u0e1e\u0e31\u0e19\u0e18\u0e4c","TRD_QTY":"23.00","TRD_AMOUNT_PRICE":"32444.95"},{"DI_MONTH_NAME":"\u0e01\u0e38\u0e21\u0e20\u0e32\u0e1e\u0e31\u0e19\u0e18\u0e4c","TRD_QTY":"76.00","TRD_AMOUNT_PRICE":"118420.00"},{"DI_MONTH_NAME":"\u0e01\u0e38\u0e21\u0e20\u0e32\u0e1e\u0e31\u0e19\u0e18\u0e4c","TRD_QTY":"250.00","TRD_AMOUNT_PRICE":"443940.00"},{"DI_MONTH_NAME":"\u0e01\u0e38\u0e21\u0e20\u0e32\u0e1e\u0e31\u0e19\u0e18\u0e4c","TRD_QTY":"2183.00","TRD_AMOUNT_PRICE":"3420197.77"},{"DI_MONTH_NAME":"\u0e01\u0e38\u0e21\u0e20\u0e32\u0e1e\u0e31\u0e19\u0e18\u0e4c","TRD_QTY":"252.00","TRD_AMOUNT_PRICE":"405630.00"},{"DI_MONTH_NAME":"\u0e01\u0e38\u0e21\u0e20\u0e32\u0e1e\u0e31\u0e19\u0e18\u0e4c","TRD_QTY":"24.00","TRD_AMOUNT_PRICE":"28540.00"},{"DI_MONTH_NAME":"\u0e01\u0e38\u0e21\u0e20\u0e32\u0e1e\u0e31\u0e19\u0e18\u0e4c","TRD_QTY":"4921.00","TRD_AMOUNT_PRICE":"7029103.40"},{"DI_MONTH_NAME":"\u0e01\u0e38\u0e21\u0e20\u0e32\u0e1e\u0e31\u0e19\u0e18\u0e4c","TRD_QTY":"4.00","TRD_AMOUNT_PRICE":"7340.00"},{"DI_MONTH_NAME":"\u0e01\u0e38\u0e21\u0e20\u0e32\u0e1e\u0e31\u0e19\u0e18\u0e4c","TRD_QTY":"2.00","TRD_AMOUNT_PRICE":"4860.00"},{"DI_MONTH_NAME":"\u0e01\u0e38\u0e21\u0e20\u0e32\u0e1e\u0e31\u0e19\u0e18\u0e4c","TRD_QTY":"85.00","TRD_AMOUNT_PRICE":"183308.00"},{"DI_MONTH_NAME":"\u0e01\u0e38\u0e21\u0e20\u0e32\u0e1e\u0e31\u0e19\u0e18\u0e4c","TRD_QTY":"1849.00","TRD_AMOUNT_PRICE":"2937083.80"},{"DI_MONTH_NAME":"\u0e01\u0e38\u0e21\u0e20\u0e32\u0e1e\u0e31\u0e19\u0e18\u0e4c","TRD_QTY":"434.00","TRD_AMOUNT_PRICE":"697550.00"},{"DI_MONTH_NAME":"\u0e01\u0e38\u0e21\u0e20\u0e32\u0e1e\u0e31\u0e19\u0e18\u0e4c","TRD_QTY":"535.00","TRD_AMOUNT_PRICE":"776640.00"},{"DI_MONTH_NAME":"\u0e01\u0e38\u0e21\u0e20\u0e32\u0e1e\u0e31\u0e19\u0e18\u0e4c","TRD_QTY":"105.00","TRD_AMOUNT_PRICE":"171810.00"},{"DI_MONTH_NAME":"\u0e01\u0e38\u0e21\u0e20\u0e32\u0e1e\u0e31\u0e19\u0e18\u0e4c","TRD_QTY":"36.00","TRD_AMOUNT_PRICE":"81800.00"},{"DI_MONTH_NAME":"\u0e01\u0e38\u0e21\u0e20\u0e32\u0e1e\u0e31\u0e19\u0e18\u0e4c","TRD_QTY":"4.00","TRD_AMOUNT_PRICE":"5319.00"},{"DI_MONTH_NAME":"\u0e01\u0e38\u0e21\u0e20\u0e32\u0e1e\u0e31\u0e19\u0e18\u0e4c","TRD_QTY":"10.00","TRD_AMOUNT_PRICE":"20192.40"},{"DI_MONTH_NAME":"\u0e01\u0e38\u0e21\u0e20\u0e32\u0e1e\u0e31\u0e19\u0e18\u0e4c","TRD_QTY":"137.00","TRD_AMOUNT_PRICE":"208929.20"},{"DI_MONTH_NAME":"\u0e01\u0e38\u0e21\u0e20\u0e32\u0e1e\u0e31\u0e19\u0e18\u0e4c","TRD_QTY":"4.00","TRD_AMOUNT_PRICE":"10204.60"},{"DI_MONTH_NAME":"\u0e01\u0e38\u0e21\u0e20\u0e32\u0e1e\u0e31\u0e19\u0e18\u0e4c","TRD_QTY":"341.00","TRD_AMOUNT_PRICE":"537334.40"},{"DI_MONTH_NAME":"\u0e01\u0e38\u0e21\u0e20\u0e32\u0e1e\u0e31\u0e19\u0e18\u0e4c","TRD_QTY":"871.00","TRD_AMOUNT_PRICE":"1302972.55"},{"DI_MONTH_NAME":"\u0e01\u0e38\u0e21\u0e20\u0e32\u0e1e\u0e31\u0e19\u0e18\u0e4c","TRD_QTY":"727.00","TRD_AMOUNT_PRICE":"1197680.00"},{"DI_MONTH_NAME":"\u0e01\u0e38\u0e21\u0e20\u0e32\u0e1e\u0e31\u0e19\u0e18\u0e4c","TRD_QTY":"380.00","TRD_AMOUNT_PRICE":"659179.70"},{"DI_MONTH_NAME":"\u0e01\u0e38\u0e21\u0e20\u0e32\u0e1e\u0e31\u0e19\u0e18\u0e4c","TRD_QTY":"494.00","TRD_AMOUNT_PRICE":"1234062.60"},{"DI_MONTH_NAME":"\u0e01\u0e38\u0e21\u0e20\u0e32\u0e1e\u0e31\u0e19\u0e18\u0e4c","TRD_QTY":"177.00","TRD_AMOUNT_PRICE":"239811.20"},{"DI_MONTH_NAME":"\u0e01\u0e38\u0e21\u0e20\u0e32\u0e1e\u0e31\u0e19\u0e18\u0e4c","TRD_QTY":"1053.00","TRD_AMOUNT_PRICE":"1642580.00"},{"DI_MONTH_NAME":"\u0e01\u0e38\u0e21\u0e20\u0e32\u0e1e\u0e31\u0e19\u0e18\u0e4c","TRD_QTY":"43.00","TRD_AMOUNT_PRICE":"75220.00"},{"DI_MONTH_NAME":"\u0e01\u0e38\u0e21\u0e20\u0e32\u0e1e\u0e31\u0e19\u0e18\u0e4c","TRD_QTY":"4.00","TRD_AMOUNT_PRICE":"10080.00"},{"DI_MONTH_NAME":"\u0e01\u0e38\u0e21\u0e20\u0e32\u0e1e\u0e31\u0e19\u0e18\u0e4c","TRD_QTY":"18.00","TRD_AMOUNT_PRICE":"32980.00"},{"DI_MONTH_NAME":"\u0e01\u0e38\u0e21\u0e20\u0e32\u0e1e\u0e31\u0e19\u0e18\u0e4c","TRD_QTY":"60.00","TRD_AMOUNT_PRICE":"80480.00"},{"DI_MONTH_NAME":"\u0e01\u0e38\u0e21\u0e20\u0e32\u0e1e\u0e31\u0e19\u0e18\u0e4c","TRD_QTY":"2.00","TRD_AMOUNT_PRICE":"2860.00"},{"DI_MONTH_NAME":"\u0e01\u0e38\u0e21\u0e20\u0e32\u0e1e\u0e31\u0e19\u0e18\u0e4c","TRD_QTY":"48.00","TRD_AMOUNT_PRICE":"58840.00"},{"DI_MONTH_NAME":"\u0e01\u0e38\u0e21\u0e20\u0e32\u0e1e\u0e31\u0e19\u0e18\u0e4c","TRD_QTY":"28.00","TRD_AMOUNT_PRICE":"42680.00"},{"DI_MONTH_NAME":"\u0e01\u0e38\u0e21\u0e20\u0e32\u0e1e\u0e31\u0e19\u0e18\u0e4c","TRD_QTY":"164.00","TRD_AMOUNT_PRICE":"178160.00"},{"DI_MONTH_NAME":"\u0e01\u0e38\u0e21\u0e20\u0e32\u0e1e\u0e31\u0e19\u0e18\u0e4c","TRD_QTY":"128.00","TRD_AMOUNT_PRICE":"232540.00"},{"DI_MONTH_NAME":"\u0e21\u0e35\u0e19\u0e32\u0e04\u0e21","TRD_QTY":"4.00","TRD_AMOUNT_PRICE":"8279.00"},{"DI_MONTH_NAME":"\u0e21\u0e35\u0e19\u0e32\u0e04\u0e21","TRD_QTY":"5190.00","TRD_AMOUNT_PRICE":"8231533.45"},{"DI_MONTH_NAME":"\u0e21\u0e35\u0e19\u0e32\u0e04\u0e21","TRD_QTY":"314.00","TRD_AMOUNT_PRICE":"499100.00"},{"DI_MONTH_NAME":"\u0e21\u0e35\u0e19\u0e32\u0e04\u0e21","TRD_QTY":"193.00","TRD_AMOUNT_PRICE":"304590.00"},{"DI_MONTH_NAME":"\u0e21\u0e35\u0e19\u0e32\u0e04\u0e21","TRD_QTY":"143.00","TRD_AMOUNT_PRICE":"244338.24"},{"DI_MONTH_NAME":"\u0e21\u0e35\u0e19\u0e32\u0e04\u0e21","TRD_QTY":"172.00","TRD_AMOUNT_PRICE":"254450.00"},{"DI_MONTH_NAME":"\u0e21\u0e35\u0e19\u0e32\u0e04\u0e21","TRD_QTY":"768.00","TRD_AMOUNT_PRICE":"1128725.60"},{"DI_MONTH_NAME":"\u0e21\u0e35\u0e19\u0e32\u0e04\u0e21","TRD_QTY":"231.00","TRD_AMOUNT_PRICE":"373635.20"},{"DI_MONTH_NAME":"\u0e21\u0e35\u0e19\u0e32\u0e04\u0e21","TRD_QTY":"16.00","TRD_AMOUNT_PRICE":"28200.00"},{"DI_MONTH_NAME":"\u0e21\u0e35\u0e19\u0e32\u0e04\u0e21","TRD_QTY":"38.00","TRD_AMOUNT_PRICE":"40622.79"},{"DI_MONTH_NAME":"\u0e21\u0e35\u0e19\u0e32\u0e04\u0e21","TRD_QTY":"19.00","TRD_AMOUNT_PRICE":"16770.00"},{"DI_MONTH_NAME":"\u0e21\u0e35\u0e19\u0e32\u0e04\u0e21","TRD_QTY":"120.00","TRD_AMOUNT_PRICE":"183180.00"},{"DI_MONTH_NAME":"\u0e21\u0e35\u0e19\u0e32\u0e04\u0e21","TRD_QTY":"226.00","TRD_AMOUNT_PRICE":"390640.00"},{"DI_MONTH_NAME":"\u0e21\u0e35\u0e19\u0e32\u0e04\u0e21","TRD_QTY":"2438.00","TRD_AMOUNT_PRICE":"3775926.00"},{"DI_MONTH_NAME":"\u0e21\u0e35\u0e19\u0e32\u0e04\u0e21","TRD_QTY":"370.00","TRD_AMOUNT_PRICE":"640055.70"},{"DI_MONTH_NAME":"\u0e21\u0e35\u0e19\u0e32\u0e04\u0e21","TRD_QTY":"79.00","TRD_AMOUNT_PRICE":"105250.95"},{"DI_MONTH_NAME":"\u0e21\u0e35\u0e19\u0e32\u0e04\u0e21","TRD_QTY":"5795.00","TRD_AMOUNT_PRICE":"7848107.94"},{"DI_MONTH_NAME":"\u0e21\u0e35\u0e19\u0e32\u0e04\u0e21","TRD_QTY":"109.00","TRD_AMOUNT_PRICE":"228070.00"},{"DI_MONTH_NAME":"\u0e21\u0e35\u0e19\u0e32\u0e04\u0e21","TRD_QTY":"2399.00","TRD_AMOUNT_PRICE":"3726158.00"},{"DI_MONTH_NAME":"\u0e21\u0e35\u0e19\u0e32\u0e04\u0e21","TRD_QTY":"556.00","TRD_AMOUNT_PRICE":"861550.00"},{"DI_MONTH_NAME":"\u0e21\u0e35\u0e19\u0e32\u0e04\u0e21","TRD_QTY":"1121.00","TRD_AMOUNT_PRICE":"1734373.44"},{"DI_MONTH_NAME":"\u0e21\u0e35\u0e19\u0e32\u0e04\u0e21","TRD_QTY":"192.00","TRD_AMOUNT_PRICE":"268030.00"},{"DI_MONTH_NAME":"\u0e21\u0e35\u0e19\u0e32\u0e04\u0e21","TRD_QTY":"219.00","TRD_AMOUNT_PRICE":"189580.00"},{"DI_MONTH_NAME":"\u0e21\u0e35\u0e19\u0e32\u0e04\u0e21","TRD_QTY":"8.00","TRD_AMOUNT_PRICE":"13435.40"},{"DI_MONTH_NAME":"\u0e21\u0e35\u0e19\u0e32\u0e04\u0e21","TRD_QTY":"4.00","TRD_AMOUNT_PRICE":"9000.00"},{"DI_MONTH_NAME":"\u0e21\u0e35\u0e19\u0e32\u0e04\u0e21","TRD_QTY":"5.00","TRD_AMOUNT_PRICE":"11337.35"},{"DI_MONTH_NAME":"\u0e21\u0e35\u0e19\u0e32\u0e04\u0e21","TRD_QTY":"171.00","TRD_AMOUNT_PRICE":"213698.15"},{"DI_MONTH_NAME":"\u0e21\u0e35\u0e19\u0e32\u0e04\u0e21","TRD_QTY":"12.00","TRD_AMOUNT_PRICE":"23837.00"},{"DI_MONTH_NAME":"\u0e21\u0e35\u0e19\u0e32\u0e04\u0e21","TRD_QTY":"4.00","TRD_AMOUNT_PRICE":"10529.65"},{"DI_MONTH_NAME":"\u0e21\u0e35\u0e19\u0e32\u0e04\u0e21","TRD_QTY":"226.00","TRD_AMOUNT_PRICE":"355360.00"},{"DI_MONTH_NAME":"\u0e21\u0e35\u0e19\u0e32\u0e04\u0e21","TRD_QTY":"9.00","TRD_AMOUNT_PRICE":"24390.00"},{"DI_MONTH_NAME":"\u0e21\u0e35\u0e19\u0e32\u0e04\u0e21","TRD_QTY":"1.00","TRD_AMOUNT_PRICE":"1080.00"},{"DI_MONTH_NAME":"\u0e21\u0e35\u0e19\u0e32\u0e04\u0e21","TRD_QTY":"988.00","TRD_AMOUNT_PRICE":"1743366.30"},{"DI_MONTH_NAME":"\u0e21\u0e35\u0e19\u0e32\u0e04\u0e21","TRD_QTY":"895.00","TRD_AMOUNT_PRICE":"1431161.40"},{"DI_MONTH_NAME":"\u0e21\u0e35\u0e19\u0e32\u0e04\u0e21","TRD_QTY":"490.00","TRD_AMOUNT_PRICE":"800904.75"},{"DI_MONTH_NAME":"\u0e21\u0e35\u0e19\u0e32\u0e04\u0e21","TRD_QTY":"421.00","TRD_AMOUNT_PRICE":"1096440.00"},{"DI_MONTH_NAME":"\u0e21\u0e35\u0e19\u0e32\u0e04\u0e21","TRD_QTY":"182.00","TRD_AMOUNT_PRICE":"297160.00"},{"DI_MONTH_NAME":"\u0e21\u0e35\u0e19\u0e32\u0e04\u0e21","TRD_QTY":"984.00","TRD_AMOUNT_PRICE":"1511714.25"},{"DI_MONTH_NAME":"\u0e21\u0e35\u0e19\u0e32\u0e04\u0e21","TRD_QTY":"4.00","TRD_AMOUNT_PRICE":"3600.00"},{"DI_MONTH_NAME":"\u0e21\u0e35\u0e19\u0e32\u0e04\u0e21","TRD_QTY":"12.00","TRD_AMOUNT_PRICE":"25760.00"},{"DI_MONTH_NAME":"\u0e21\u0e35\u0e19\u0e32\u0e04\u0e21","TRD_QTY":"12.00","TRD_AMOUNT_PRICE":"28880.00"},{"DI_MONTH_NAME":"\u0e21\u0e35\u0e19\u0e32\u0e04\u0e21","TRD_QTY":"7.00","TRD_AMOUNT_PRICE":"14230.00"},{"DI_MONTH_NAME":"\u0e21\u0e35\u0e19\u0e32\u0e04\u0e21","TRD_QTY":"20.00","TRD_AMOUNT_PRICE":"29000.00"},{"DI_MONTH_NAME":"\u0e21\u0e35\u0e19\u0e32\u0e04\u0e21","TRD_QTY":"18.00","TRD_AMOUNT_PRICE":"23623.10"},{"DI_MONTH_NAME":"\u0e21\u0e35\u0e19\u0e32\u0e04\u0e21","TRD_QTY":"48.00","TRD_AMOUNT_PRICE":"66024.00"},{"DI_MONTH_NAME":"\u0e21\u0e35\u0e19\u0e32\u0e04\u0e21","TRD_QTY":"72.00","TRD_AMOUNT_PRICE":"88581.20"},{"DI_MONTH_NAME":"\u0e21\u0e35\u0e19\u0e32\u0e04\u0e21","TRD_QTY":"158.00","TRD_AMOUNT_PRICE":"290280.00"},{"DI_MONTH_NAME":"\u0e21\u0e35\u0e19\u0e32\u0e04\u0e21","TRD_QTY":"72.00","TRD_AMOUNT_PRICE":"93160.00"},{"DI_MONTH_NAME":"\u0e40\u0e21\u0e29\u0e32\u0e22\u0e19","TRD_QTY":"4552.00","TRD_AMOUNT_PRICE":"6802569.70"},{"DI_MONTH_NAME":"\u0e40\u0e21\u0e29\u0e32\u0e22\u0e19","TRD_QTY":"291.00","TRD_AMOUNT_PRICE":"487610.00"},{"DI_MONTH_NAME":"\u0e40\u0e21\u0e29\u0e32\u0e22\u0e19","TRD_QTY":"1.00","TRD_AMOUNT_PRICE":"1625.25"},{"DI_MONTH_NAME":"\u0e40\u0e21\u0e29\u0e32\u0e22\u0e19","TRD_QTY":"247.00","TRD_AMOUNT_PRICE":"422330.00"},{"DI_MONTH_NAME":"\u0e40\u0e21\u0e29\u0e32\u0e22\u0e19","TRD_QTY":"6.00","TRD_AMOUNT_PRICE":"8199.00"},{"DI_MONTH_NAME":"\u0e40\u0e21\u0e29\u0e32\u0e22\u0e19","TRD_QTY":"157.00","TRD_AMOUNT_PRICE":"445920.00"},{"DI_MONTH_NAME":"\u0e40\u0e21\u0e29\u0e32\u0e22\u0e19","TRD_QTY":"238.00","TRD_AMOUNT_PRICE":"362480.65"},{"DI_MONTH_NAME":"\u0e40\u0e21\u0e29\u0e32\u0e22\u0e19","TRD_QTY":"579.00","TRD_AMOUNT_PRICE":"786070.00"},{"DI_MONTH_NAME":"\u0e40\u0e21\u0e29\u0e32\u0e22\u0e19","TRD_QTY":"49.00","TRD_AMOUNT_PRICE":"73980.00"},{"DI_MONTH_NAME":"\u0e40\u0e21\u0e29\u0e32\u0e22\u0e19","TRD_QTY":"5.00","TRD_AMOUNT_PRICE":"15100.00"},{"DI_MONTH_NAME":"\u0e40\u0e21\u0e29\u0e32\u0e22\u0e19","TRD_QTY":"9.00","TRD_AMOUNT_PRICE":"13532.40"},{"DI_MONTH_NAME":"\u0e40\u0e21\u0e29\u0e32\u0e22\u0e19","TRD_QTY":"94.00","TRD_AMOUNT_PRICE":"152300.00"},{"DI_MONTH_NAME":"\u0e40\u0e21\u0e29\u0e32\u0e22\u0e19","TRD_QTY":"269.00","TRD_AMOUNT_PRICE":"486700.00"},{"DI_MONTH_NAME":"\u0e40\u0e21\u0e29\u0e32\u0e22\u0e19","TRD_QTY":"2618.00","TRD_AMOUNT_PRICE":"4217030.20"},{"DI_MONTH_NAME":"\u0e40\u0e21\u0e29\u0e32\u0e22\u0e19","TRD_QTY":"504.00","TRD_AMOUNT_PRICE":"859895.10"},{"DI_MONTH_NAME":"\u0e40\u0e21\u0e29\u0e32\u0e22\u0e19","TRD_QTY":"26.00","TRD_AMOUNT_PRICE":"32780.00"},{"DI_MONTH_NAME":"\u0e40\u0e21\u0e29\u0e32\u0e22\u0e19","TRD_QTY":"5781.00","TRD_AMOUNT_PRICE":"8180034.60"},{"DI_MONTH_NAME":"\u0e40\u0e21\u0e29\u0e32\u0e22\u0e19","TRD_QTY":"200.00","TRD_AMOUNT_PRICE":"422420.00"},{"DI_MONTH_NAME":"\u0e40\u0e21\u0e29\u0e32\u0e22\u0e19","TRD_QTY":"2679.00","TRD_AMOUNT_PRICE":"3926399.75"},{"DI_MONTH_NAME":"\u0e40\u0e21\u0e29\u0e32\u0e22\u0e19","TRD_QTY":"389.00","TRD_AMOUNT_PRICE":"584457.85"},{"DI_MONTH_NAME":"\u0e40\u0e21\u0e29\u0e32\u0e22\u0e19","TRD_QTY":"707.00","TRD_AMOUNT_PRICE":"1040990.00"},{"DI_MONTH_NAME":"\u0e40\u0e21\u0e29\u0e32\u0e22\u0e19","TRD_QTY":"113.00","TRD_AMOUNT_PRICE":"193320.00"},{"DI_MONTH_NAME":"\u0e40\u0e21\u0e29\u0e32\u0e22\u0e19","TRD_QTY":"732.00","TRD_AMOUNT_PRICE":"870910.00"},{"DI_MONTH_NAME":"\u0e40\u0e21\u0e29\u0e32\u0e22\u0e19","TRD_QTY":"2.00","TRD_AMOUNT_PRICE":"2561.00"},{"DI_MONTH_NAME":"\u0e40\u0e21\u0e29\u0e32\u0e22\u0e19","TRD_QTY":"2.00","TRD_AMOUNT_PRICE":"2777.70"},{"DI_MONTH_NAME":"\u0e40\u0e21\u0e29\u0e32\u0e22\u0e19","TRD_QTY":"74.00","TRD_AMOUNT_PRICE":"107339.00"},{"DI_MONTH_NAME":"\u0e40\u0e21\u0e29\u0e32\u0e22\u0e19","TRD_QTY":"6.00","TRD_AMOUNT_PRICE":"7003.35"},{"DI_MONTH_NAME":"\u0e40\u0e21\u0e29\u0e32\u0e22\u0e19","TRD_QTY":"479.00","TRD_AMOUNT_PRICE":"694020.00"},{"DI_MONTH_NAME":"\u0e40\u0e21\u0e29\u0e32\u0e22\u0e19","TRD_QTY":"52.00","TRD_AMOUNT_PRICE":"89600.00"},{"DI_MONTH_NAME":"\u0e40\u0e21\u0e29\u0e32\u0e22\u0e19","TRD_QTY":"1078.00","TRD_AMOUNT_PRICE":"1759607.36"},{"DI_MONTH_NAME":"\u0e40\u0e21\u0e29\u0e32\u0e22\u0e19","TRD_QTY":"922.00","TRD_AMOUNT_PRICE":"1358130.00"},{"DI_MONTH_NAME":"\u0e40\u0e21\u0e29\u0e32\u0e22\u0e19","TRD_QTY":"290.00","TRD_AMOUNT_PRICE":"539717.00"},{"DI_MONTH_NAME":"\u0e40\u0e21\u0e29\u0e32\u0e22\u0e19","TRD_QTY":"375.00","TRD_AMOUNT_PRICE":"899042.00"},{"DI_MONTH_NAME":"\u0e40\u0e21\u0e29\u0e32\u0e22\u0e19","TRD_QTY":"136.00","TRD_AMOUNT_PRICE":"211770.00"},{"DI_MONTH_NAME":"\u0e40\u0e21\u0e29\u0e32\u0e22\u0e19","TRD_QTY":"941.00","TRD_AMOUNT_PRICE":"1450126.70"},{"DI_MONTH_NAME":"\u0e40\u0e21\u0e29\u0e32\u0e22\u0e19","TRD_QTY":"1.00","TRD_AMOUNT_PRICE":"3250.50"},{"DI_MONTH_NAME":"\u0e40\u0e21\u0e29\u0e32\u0e22\u0e19","TRD_QTY":"16.00","TRD_AMOUNT_PRICE":"34440.00"},{"DI_MONTH_NAME":"\u0e40\u0e21\u0e29\u0e32\u0e22\u0e19","TRD_QTY":"12.00","TRD_AMOUNT_PRICE":"26000.00"},{"DI_MONTH_NAME":"\u0e40\u0e21\u0e29\u0e32\u0e22\u0e19","TRD_QTY":"1.00","TRD_AMOUNT_PRICE":"3191.40"},{"DI_MONTH_NAME":"\u0e40\u0e21\u0e29\u0e32\u0e22\u0e19","TRD_QTY":"27.00","TRD_AMOUNT_PRICE":"52970.00"},{"DI_MONTH_NAME":"\u0e40\u0e21\u0e29\u0e32\u0e22\u0e19","TRD_QTY":"16.00","TRD_AMOUNT_PRICE":"25400.00"},{"DI_MONTH_NAME":"\u0e40\u0e21\u0e29\u0e32\u0e22\u0e19","TRD_QTY":"78.00","TRD_AMOUNT_PRICE":"100391.08"},{"DI_MONTH_NAME":"\u0e40\u0e21\u0e29\u0e32\u0e22\u0e19","TRD_QTY":"16.00","TRD_AMOUNT_PRICE":"21800.00"},{"DI_MONTH_NAME":"\u0e40\u0e21\u0e29\u0e32\u0e22\u0e19","TRD_QTY":"78.00","TRD_AMOUNT_PRICE":"140132.40"},{"DI_MONTH_NAME":"\u0e40\u0e21\u0e29\u0e32\u0e22\u0e19","TRD_QTY":"168.00","TRD_AMOUNT_PRICE":"294430.00"},{"DI_MONTH_NAME":"\u0e40\u0e21\u0e29\u0e32\u0e22\u0e19","TRD_QTY":"4.00","TRD_AMOUNT_PRICE":"5880.00"},{"DI_MONTH_NAME":"\u0e40\u0e21\u0e29\u0e32\u0e22\u0e19","TRD_QTY":"28.00","TRD_AMOUNT_PRICE":"47600.00"},{"DI_MONTH_NAME":"\u0e1e\u0e24\u0e29\u0e20\u0e32\u0e04\u0e21","TRD_QTY":"40.00","TRD_AMOUNT_PRICE":"61430.00"},{"DI_MONTH_NAME":"\u0e1e\u0e24\u0e29\u0e20\u0e32\u0e04\u0e21","TRD_QTY":"5431.00","TRD_AMOUNT_PRICE":"8293516.20"},{"DI_MONTH_NAME":"\u0e1e\u0e24\u0e29\u0e20\u0e32\u0e04\u0e21","TRD_QTY":"202.00","TRD_AMOUNT_PRICE":"382480.00"},{"DI_MONTH_NAME":"\u0e1e\u0e24\u0e29\u0e20\u0e32\u0e04\u0e21","TRD_QTY":"3.00","TRD_AMOUNT_PRICE":"7092.00"},{"DI_MONTH_NAME":"\u0e1e\u0e24\u0e29\u0e20\u0e32\u0e04\u0e21","TRD_QTY":"151.00","TRD_AMOUNT_PRICE":"262482.40"},{"DI_MONTH_NAME":"\u0e1e\u0e24\u0e29\u0e20\u0e32\u0e04\u0e21","TRD_QTY":"8.00","TRD_AMOUNT_PRICE":"15070.50"},{"DI_MONTH_NAME":"\u0e1e\u0e24\u0e29\u0e20\u0e32\u0e04\u0e21","TRD_QTY":"231.00","TRD_AMOUNT_PRICE":"380160.00"},{"DI_MONTH_NAME":"\u0e1e\u0e24\u0e29\u0e20\u0e32\u0e04\u0e21","TRD_QTY":"169.00","TRD_AMOUNT_PRICE":"236492.80"},{"DI_MONTH_NAME":"\u0e1e\u0e24\u0e29\u0e20\u0e32\u0e04\u0e21","TRD_QTY":"509.00","TRD_AMOUNT_PRICE":"704964.00"},{"DI_MONTH_NAME":"\u0e1e\u0e24\u0e29\u0e20\u0e32\u0e04\u0e21","TRD_QTY":"106.00","TRD_AMOUNT_PRICE":"164320.00"},{"DI_MONTH_NAME":"\u0e1e\u0e24\u0e29\u0e20\u0e32\u0e04\u0e21","TRD_QTY":"10.00","TRD_AMOUNT_PRICE":"15300.00"},{"DI_MONTH_NAME":"\u0e1e\u0e24\u0e29\u0e20\u0e32\u0e04\u0e21","TRD_QTY":"1.00","TRD_AMOUNT_PRICE":"2076.00"},{"DI_MONTH_NAME":"\u0e1e\u0e24\u0e29\u0e20\u0e32\u0e04\u0e21","TRD_QTY":"4.00","TRD_AMOUNT_PRICE":"7289.00"},{"DI_MONTH_NAME":"\u0e1e\u0e24\u0e29\u0e20\u0e32\u0e04\u0e21","TRD_QTY":"103.00","TRD_AMOUNT_PRICE":"170400.00"},{"DI_MONTH_NAME":"\u0e1e\u0e24\u0e29\u0e20\u0e32\u0e04\u0e21","TRD_QTY":"286.00","TRD_AMOUNT_PRICE":"532590.00"},{"DI_MONTH_NAME":"\u0e1e\u0e24\u0e29\u0e20\u0e32\u0e04\u0e21","TRD_QTY":"3697.00","TRD_AMOUNT_PRICE":"5426579.60"},{"DI_MONTH_NAME":"\u0e1e\u0e24\u0e29\u0e20\u0e32\u0e04\u0e21","TRD_QTY":"519.00","TRD_AMOUNT_PRICE":"851077.90"},{"DI_MONTH_NAME":"\u0e1e\u0e24\u0e29\u0e20\u0e32\u0e04\u0e21","TRD_QTY":"4.00","TRD_AMOUNT_PRICE":"26752.60"},{"DI_MONTH_NAME":"\u0e1e\u0e24\u0e29\u0e20\u0e32\u0e04\u0e21","TRD_QTY":"68.00","TRD_AMOUNT_PRICE":"82670.00"},{"DI_MONTH_NAME":"\u0e1e\u0e24\u0e29\u0e20\u0e32\u0e04\u0e21","TRD_QTY":"7291.00","TRD_AMOUNT_PRICE":"10118031.10"},{"DI_MONTH_NAME":"\u0e1e\u0e24\u0e29\u0e20\u0e32\u0e04\u0e21","TRD_QTY":"55.00","TRD_AMOUNT_PRICE":"87250.00"},{"DI_MONTH_NAME":"\u0e1e\u0e24\u0e29\u0e20\u0e32\u0e04\u0e21","TRD_QTY":"80.00","TRD_AMOUNT_PRICE":"177770.00"},{"DI_MONTH_NAME":"\u0e1e\u0e24\u0e29\u0e20\u0e32\u0e04\u0e21","TRD_QTY":"2493.00","TRD_AMOUNT_PRICE":"3841148.15"},{"DI_MONTH_NAME":"\u0e1e\u0e24\u0e29\u0e20\u0e32\u0e04\u0e21","TRD_QTY":"542.00","TRD_AMOUNT_PRICE":"896030.00"},{"DI_MONTH_NAME":"\u0e1e\u0e24\u0e29\u0e20\u0e32\u0e04\u0e21","TRD_QTY":"780.00","TRD_AMOUNT_PRICE":"1242610.00"},{"DI_MONTH_NAME":"\u0e1e\u0e24\u0e29\u0e20\u0e32\u0e04\u0e21","TRD_QTY":"107.00","TRD_AMOUNT_PRICE":"188150.00"},{"DI_MONTH_NAME":"\u0e1e\u0e24\u0e29\u0e20\u0e32\u0e04\u0e21","TRD_QTY":"46.00","TRD_AMOUNT_PRICE":"41180.00"},{"DI_MONTH_NAME":"\u0e1e\u0e24\u0e29\u0e20\u0e32\u0e04\u0e21","TRD_QTY":"13.00","TRD_AMOUNT_PRICE":"20570.00"},{"DI_MONTH_NAME":"\u0e1e\u0e24\u0e29\u0e20\u0e32\u0e04\u0e21","TRD_QTY":"2.00","TRD_AMOUNT_PRICE":"1536.60"},{"DI_MONTH_NAME":"\u0e1e\u0e24\u0e29\u0e20\u0e32\u0e04\u0e21","TRD_QTY":"99.00","TRD_AMOUNT_PRICE":"138131.90"},{"DI_MONTH_NAME":"\u0e1e\u0e24\u0e29\u0e20\u0e32\u0e04\u0e21","TRD_QTY":"8.00","TRD_AMOUNT_PRICE":"19010.50"},{"DI_MONTH_NAME":"\u0e1e\u0e24\u0e29\u0e20\u0e32\u0e04\u0e21","TRD_QTY":"322.00","TRD_AMOUNT_PRICE":"510380.00"},{"DI_MONTH_NAME":"\u0e1e\u0e24\u0e29\u0e20\u0e32\u0e04\u0e21","TRD_QTY":"4.00","TRD_AMOUNT_PRICE":"7680.00"},{"DI_MONTH_NAME":"\u0e1e\u0e24\u0e29\u0e20\u0e32\u0e04\u0e21","TRD_QTY":"635.00","TRD_AMOUNT_PRICE":"1023986.70"},{"DI_MONTH_NAME":"\u0e1e\u0e24\u0e29\u0e20\u0e32\u0e04\u0e21","TRD_QTY":"1129.00","TRD_AMOUNT_PRICE":"1833284.60"},{"DI_MONTH_NAME":"\u0e1e\u0e24\u0e29\u0e20\u0e32\u0e04\u0e21","TRD_QTY":"337.00","TRD_AMOUNT_PRICE":"639505.75"},{"DI_MONTH_NAME":"\u0e1e\u0e24\u0e29\u0e20\u0e32\u0e04\u0e21","TRD_QTY":"320.00","TRD_AMOUNT_PRICE":"788318.70"},{"DI_MONTH_NAME":"\u0e1e\u0e24\u0e29\u0e20\u0e32\u0e04\u0e21","TRD_QTY":"204.00","TRD_AMOUNT_PRICE":"313750.00"},{"DI_MONTH_NAME":"\u0e1e\u0e24\u0e29\u0e20\u0e32\u0e04\u0e21","TRD_QTY":"868.00","TRD_AMOUNT_PRICE":"1318962.25"},{"DI_MONTH_NAME":"\u0e1e\u0e24\u0e29\u0e20\u0e32\u0e04\u0e21","TRD_QTY":"4.00","TRD_AMOUNT_PRICE":"7700.00"},{"DI_MONTH_NAME":"\u0e1e\u0e24\u0e29\u0e20\u0e32\u0e04\u0e21","TRD_QTY":"19.00","TRD_AMOUNT_PRICE":"36340.00"},{"DI_MONTH_NAME":"\u0e1e\u0e24\u0e29\u0e20\u0e32\u0e04\u0e21","TRD_QTY":"51.00","TRD_AMOUNT_PRICE":"79630.00"},{"DI_MONTH_NAME":"\u0e1e\u0e24\u0e29\u0e20\u0e32\u0e04\u0e21","TRD_QTY":"5.00","TRD_AMOUNT_PRICE":"12253.40"},{"DI_MONTH_NAME":"\u0e1e\u0e24\u0e29\u0e20\u0e32\u0e04\u0e21","TRD_QTY":"1.00","TRD_AMOUNT_PRICE":"1940.00"},{"DI_MONTH_NAME":"\u0e1e\u0e24\u0e29\u0e20\u0e32\u0e04\u0e21","TRD_QTY":"59.00","TRD_AMOUNT_PRICE":"92220.00"},{"DI_MONTH_NAME":"\u0e1e\u0e24\u0e29\u0e20\u0e32\u0e04\u0e21","TRD_QTY":"4.00","TRD_AMOUNT_PRICE":"27993.70"},{"DI_MONTH_NAME":"\u0e1e\u0e24\u0e29\u0e20\u0e32\u0e04\u0e21","TRD_QTY":"23.00","TRD_AMOUNT_PRICE":"28676.15"},{"DI_MONTH_NAME":"\u0e1e\u0e24\u0e29\u0e20\u0e32\u0e04\u0e21","TRD_QTY":"20.00","TRD_AMOUNT_PRICE":"22160.00"},{"DI_MONTH_NAME":"\u0e1e\u0e24\u0e29\u0e20\u0e32\u0e04\u0e21","TRD_QTY":"57.00","TRD_AMOUNT_PRICE":"113100.00"},{"DI_MONTH_NAME":"\u0e1e\u0e24\u0e29\u0e20\u0e32\u0e04\u0e21","TRD_QTY":"113.00","TRD_AMOUNT_PRICE":"223580.00"},{"DI_MONTH_NAME":"\u0e1e\u0e24\u0e29\u0e20\u0e32\u0e04\u0e21","TRD_QTY":"26.00","TRD_AMOUNT_PRICE":"42920.00"},{"DI_MONTH_NAME":"\u0e21\u0e34\u0e16\u0e38\u0e19\u0e32\u0e22\u0e19","TRD_QTY":"89.00","TRD_AMOUNT_PRICE":"158757.80"},{"DI_MONTH_NAME":"\u0e21\u0e34\u0e16\u0e38\u0e19\u0e32\u0e22\u0e19","TRD_QTY":"4037.00","TRD_AMOUNT_PRICE":"6399796.90"},{"DI_MONTH_NAME":"\u0e21\u0e34\u0e16\u0e38\u0e19\u0e32\u0e22\u0e19","TRD_QTY":"339.00","TRD_AMOUNT_PRICE":"555100.00"},{"DI_MONTH_NAME":"\u0e21\u0e34\u0e16\u0e38\u0e19\u0e32\u0e22\u0e19","TRD_QTY":"207.00","TRD_AMOUNT_PRICE":"316250.00"},{"DI_MONTH_NAME":"\u0e21\u0e34\u0e16\u0e38\u0e19\u0e32\u0e22\u0e19","TRD_QTY":"125.00","TRD_AMOUNT_PRICE":"229460.00"},{"DI_MONTH_NAME":"\u0e21\u0e34\u0e16\u0e38\u0e19\u0e32\u0e22\u0e19","TRD_QTY":"117.00","TRD_AMOUNT_PRICE":"170810.00"},{"DI_MONTH_NAME":"\u0e21\u0e34\u0e16\u0e38\u0e19\u0e32\u0e22\u0e19","TRD_QTY":"511.00","TRD_AMOUNT_PRICE":"798459.20"},{"DI_MONTH_NAME":"\u0e21\u0e34\u0e16\u0e38\u0e19\u0e32\u0e22\u0e19","TRD_QTY":"92.00","TRD_AMOUNT_PRICE":"156440.00"},{"DI_MONTH_NAME":"\u0e21\u0e34\u0e16\u0e38\u0e19\u0e32\u0e22\u0e19","TRD_QTY":"54.00","TRD_AMOUNT_PRICE":"126468.00"},{"DI_MONTH_NAME":"\u0e21\u0e34\u0e16\u0e38\u0e19\u0e32\u0e22\u0e19","TRD_QTY":"216.00","TRD_AMOUNT_PRICE":"163440.00"},{"DI_MONTH_NAME":"\u0e21\u0e34\u0e16\u0e38\u0e19\u0e32\u0e22\u0e19","TRD_QTY":"165.00","TRD_AMOUNT_PRICE":"292284.00"},{"DI_MONTH_NAME":"\u0e21\u0e34\u0e16\u0e38\u0e19\u0e32\u0e22\u0e19","TRD_QTY":"192.00","TRD_AMOUNT_PRICE":"414860.00"},{"DI_MONTH_NAME":"\u0e21\u0e34\u0e16\u0e38\u0e19\u0e32\u0e22\u0e19","TRD_QTY":"1516.00","TRD_AMOUNT_PRICE":"2442461.80"},{"DI_MONTH_NAME":"\u0e21\u0e34\u0e16\u0e38\u0e19\u0e32\u0e22\u0e19","TRD_QTY":"337.00","TRD_AMOUNT_PRICE":"556626.20"},{"DI_MONTH_NAME":"\u0e21\u0e34\u0e16\u0e38\u0e19\u0e32\u0e22\u0e19","TRD_QTY":"182.00","TRD_AMOUNT_PRICE":"225180.00"},{"DI_MONTH_NAME":"\u0e21\u0e34\u0e16\u0e38\u0e19\u0e32\u0e22\u0e19","TRD_QTY":"6515.00","TRD_AMOUNT_PRICE":"9002653.45"},{"DI_MONTH_NAME":"\u0e21\u0e34\u0e16\u0e38\u0e19\u0e32\u0e22\u0e19","TRD_QTY":"30.00","TRD_AMOUNT_PRICE":"54080.00"},{"DI_MONTH_NAME":"\u0e21\u0e34\u0e16\u0e38\u0e19\u0e32\u0e22\u0e19","TRD_QTY":"110.00","TRD_AMOUNT_PRICE":"240360.00"},{"DI_MONTH_NAME":"\u0e21\u0e34\u0e16\u0e38\u0e19\u0e32\u0e22\u0e19","TRD_QTY":"1820.00","TRD_AMOUNT_PRICE":"2788649.50"},{"DI_MONTH_NAME":"\u0e21\u0e34\u0e16\u0e38\u0e19\u0e32\u0e22\u0e19","TRD_QTY":"432.00","TRD_AMOUNT_PRICE":"606276.20"},{"DI_MONTH_NAME":"\u0e21\u0e34\u0e16\u0e38\u0e19\u0e32\u0e22\u0e19","TRD_QTY":"385.00","TRD_AMOUNT_PRICE":"567740.00"},{"DI_MONTH_NAME":"\u0e21\u0e34\u0e16\u0e38\u0e19\u0e32\u0e22\u0e19","TRD_QTY":"4.00","TRD_AMOUNT_PRICE":"5220.50"},{"DI_MONTH_NAME":"\u0e21\u0e34\u0e16\u0e38\u0e19\u0e32\u0e22\u0e19","TRD_QTY":"85.00","TRD_AMOUNT_PRICE":"148454.00"},{"DI_MONTH_NAME":"\u0e21\u0e34\u0e16\u0e38\u0e19\u0e32\u0e22\u0e19","TRD_QTY":"308.00","TRD_AMOUNT_PRICE":"417640.00"},{"DI_MONTH_NAME":"\u0e21\u0e34\u0e16\u0e38\u0e19\u0e32\u0e22\u0e19","TRD_QTY":"4.00","TRD_AMOUNT_PRICE":"5480.00"},{"DI_MONTH_NAME":"\u0e21\u0e34\u0e16\u0e38\u0e19\u0e32\u0e22\u0e19","TRD_QTY":"1.00","TRD_AMOUNT_PRICE":"1063.80"},{"DI_MONTH_NAME":"\u0e21\u0e34\u0e16\u0e38\u0e19\u0e32\u0e22\u0e19","TRD_QTY":"90.00","TRD_AMOUNT_PRICE":"143995.25"},{"DI_MONTH_NAME":"\u0e21\u0e34\u0e16\u0e38\u0e19\u0e32\u0e22\u0e19","TRD_QTY":"5.00","TRD_AMOUNT_PRICE":"11682.10"},{"DI_MONTH_NAME":"\u0e21\u0e34\u0e16\u0e38\u0e19\u0e32\u0e22\u0e19","TRD_QTY":"179.00","TRD_AMOUNT_PRICE":"280220.00"},{"DI_MONTH_NAME":"\u0e21\u0e34\u0e16\u0e38\u0e19\u0e32\u0e22\u0e19","TRD_QTY":"10.00","TRD_AMOUNT_PRICE":"10940.00"},{"DI_MONTH_NAME":"\u0e21\u0e34\u0e16\u0e38\u0e19\u0e32\u0e22\u0e19","TRD_QTY":"751.00","TRD_AMOUNT_PRICE":"1220583.40"},{"DI_MONTH_NAME":"\u0e21\u0e34\u0e16\u0e38\u0e19\u0e32\u0e22\u0e19","TRD_QTY":"568.00","TRD_AMOUNT_PRICE":"971235.65"},{"DI_MONTH_NAME":"\u0e21\u0e34\u0e16\u0e38\u0e19\u0e32\u0e22\u0e19","TRD_QTY":"261.00","TRD_AMOUNT_PRICE":"536232.60"},{"DI_MONTH_NAME":"\u0e21\u0e34\u0e16\u0e38\u0e19\u0e32\u0e22\u0e19","TRD_QTY":"204.00","TRD_AMOUNT_PRICE":"459611.60"},{"DI_MONTH_NAME":"\u0e21\u0e34\u0e16\u0e38\u0e19\u0e32\u0e22\u0e19","TRD_QTY":"82.00","TRD_AMOUNT_PRICE":"128270.00"},{"DI_MONTH_NAME":"\u0e21\u0e34\u0e16\u0e38\u0e19\u0e32\u0e22\u0e19","TRD_QTY":"706.00","TRD_AMOUNT_PRICE":"1136289.00"},{"DI_MONTH_NAME":"\u0e21\u0e34\u0e16\u0e38\u0e19\u0e32\u0e22\u0e19","TRD_QTY":"32.00","TRD_AMOUNT_PRICE":"65980.00"},{"DI_MONTH_NAME":"\u0e21\u0e34\u0e16\u0e38\u0e19\u0e32\u0e22\u0e19","TRD_QTY":"64.00","TRD_AMOUNT_PRICE":"93240.00"},{"DI_MONTH_NAME":"\u0e21\u0e34\u0e16\u0e38\u0e19\u0e32\u0e22\u0e19","TRD_QTY":"4.00","TRD_AMOUNT_PRICE":"5713.00"},{"DI_MONTH_NAME":"\u0e21\u0e34\u0e16\u0e38\u0e19\u0e32\u0e22\u0e19","TRD_QTY":"14.00","TRD_AMOUNT_PRICE":"28460.00"},{"DI_MONTH_NAME":"\u0e21\u0e34\u0e16\u0e38\u0e19\u0e32\u0e22\u0e19","TRD_QTY":"28.00","TRD_AMOUNT_PRICE":"31240.00"},{"DI_MONTH_NAME":"\u0e21\u0e34\u0e16\u0e38\u0e19\u0e32\u0e22\u0e19","TRD_QTY":"2.00","TRD_AMOUNT_PRICE":"4220.00"},{"DI_MONTH_NAME":"\u0e21\u0e34\u0e16\u0e38\u0e19\u0e32\u0e22\u0e19","TRD_QTY":"25.00","TRD_AMOUNT_PRICE":"49834.75"},{"DI_MONTH_NAME":"\u0e21\u0e34\u0e16\u0e38\u0e19\u0e32\u0e22\u0e19","TRD_QTY":"62.00","TRD_AMOUNT_PRICE":"118282.00"},{"DI_MONTH_NAME":"\u0e21\u0e34\u0e16\u0e38\u0e19\u0e32\u0e22\u0e19","TRD_QTY":"94.00","TRD_AMOUNT_PRICE":"187820.00"},{"DI_MONTH_NAME":"\u0e01\u0e23\u0e01\u0e0e\u0e32\u0e04\u0e21","TRD_QTY":"116.00","TRD_AMOUNT_PRICE":"295959.48"},{"DI_MONTH_NAME":"\u0e01\u0e23\u0e01\u0e0e\u0e32\u0e04\u0e21","TRD_QTY":"4641.00","TRD_AMOUNT_PRICE":"7343220.56"},{"DI_MONTH_NAME":"\u0e01\u0e23\u0e01\u0e0e\u0e32\u0e04\u0e21","TRD_QTY":"266.00","TRD_AMOUNT_PRICE":"494470.00"},{"DI_MONTH_NAME":"\u0e01\u0e23\u0e01\u0e0e\u0e32\u0e04\u0e21","TRD_QTY":"1.00","TRD_AMOUNT_PRICE":"1132.75"},{"DI_MONTH_NAME":"\u0e01\u0e23\u0e01\u0e0e\u0e32\u0e04\u0e21","TRD_QTY":"160.00","TRD_AMOUNT_PRICE":"228340.00"},{"DI_MONTH_NAME":"\u0e01\u0e23\u0e01\u0e0e\u0e32\u0e04\u0e21","TRD_QTY":"2.00","TRD_AMOUNT_PRICE":"3408.10"},{"DI_MONTH_NAME":"\u0e01\u0e23\u0e01\u0e0e\u0e32\u0e04\u0e21","TRD_QTY":"113.00","TRD_AMOUNT_PRICE":"177320.00"},{"DI_MONTH_NAME":"\u0e01\u0e23\u0e01\u0e0e\u0e32\u0e04\u0e21","TRD_QTY":"99.00","TRD_AMOUNT_PRICE":"157780.00"},{"DI_MONTH_NAME":"\u0e01\u0e23\u0e01\u0e0e\u0e32\u0e04\u0e21","TRD_QTY":"458.00","TRD_AMOUNT_PRICE":"646500.40"},{"DI_MONTH_NAME":"\u0e01\u0e23\u0e01\u0e0e\u0e32\u0e04\u0e21","TRD_QTY":"93.00","TRD_AMOUNT_PRICE":"134260.00"},{"DI_MONTH_NAME":"\u0e01\u0e23\u0e01\u0e0e\u0e32\u0e04\u0e21","TRD_QTY":"12.00","TRD_AMOUNT_PRICE":"13680.00"},{"DI_MONTH_NAME":"\u0e01\u0e23\u0e01\u0e0e\u0e32\u0e04\u0e21","TRD_QTY":"52.00","TRD_AMOUNT_PRICE":"84400.00"},{"DI_MONTH_NAME":"\u0e01\u0e23\u0e01\u0e0e\u0e32\u0e04\u0e21","TRD_QTY":"110.00","TRD_AMOUNT_PRICE":"187880.00"},{"DI_MONTH_NAME":"\u0e01\u0e23\u0e01\u0e0e\u0e32\u0e04\u0e21","TRD_QTY":"292.00","TRD_AMOUNT_PRICE":"533120.00"},{"DI_MONTH_NAME":"\u0e01\u0e23\u0e01\u0e0e\u0e32\u0e04\u0e21","TRD_QTY":"1884.00","TRD_AMOUNT_PRICE":"2880391.30"},{"DI_MONTH_NAME":"\u0e01\u0e23\u0e01\u0e0e\u0e32\u0e04\u0e21","TRD_QTY":"371.00","TRD_AMOUNT_PRICE":"613103.00"},{"DI_MONTH_NAME":"\u0e01\u0e23\u0e01\u0e0e\u0e32\u0e04\u0e21","TRD_QTY":"140.00","TRD_AMOUNT_PRICE":"173380.00"},{"DI_MONTH_NAME":"\u0e01\u0e23\u0e01\u0e0e\u0e32\u0e04\u0e21","TRD_QTY":"7093.00","TRD_AMOUNT_PRICE":"9994986.55"},{"DI_MONTH_NAME":"\u0e01\u0e23\u0e01\u0e0e\u0e32\u0e04\u0e21","TRD_QTY":"13.00","TRD_AMOUNT_PRICE":"26250.00"},{"DI_MONTH_NAME":"\u0e01\u0e23\u0e01\u0e0e\u0e32\u0e04\u0e21","TRD_QTY":"94.00","TRD_AMOUNT_PRICE":"151840.00"},{"DI_MONTH_NAME":"\u0e01\u0e23\u0e01\u0e0e\u0e32\u0e04\u0e21","TRD_QTY":"2408.00","TRD_AMOUNT_PRICE":"3778441.50"},{"DI_MONTH_NAME":"\u0e01\u0e23\u0e01\u0e0e\u0e32\u0e04\u0e21","TRD_QTY":"393.00","TRD_AMOUNT_PRICE":"522740.00"},{"DI_MONTH_NAME":"\u0e01\u0e23\u0e01\u0e0e\u0e32\u0e04\u0e21","TRD_QTY":"756.00","TRD_AMOUNT_PRICE":"1179050.60"},{"DI_MONTH_NAME":"\u0e01\u0e23\u0e01\u0e0e\u0e32\u0e04\u0e21","TRD_QTY":"86.00","TRD_AMOUNT_PRICE":"169990.00"},{"DI_MONTH_NAME":"\u0e01\u0e23\u0e01\u0e0e\u0e32\u0e04\u0e21","TRD_QTY":"150.00","TRD_AMOUNT_PRICE":"346340.00"},{"DI_MONTH_NAME":"\u0e01\u0e23\u0e01\u0e0e\u0e32\u0e04\u0e21","TRD_QTY":"4.00","TRD_AMOUNT_PRICE":"5520.00"},{"DI_MONTH_NAME":"\u0e01\u0e23\u0e01\u0e0e\u0e32\u0e04\u0e21","TRD_QTY":"121.00","TRD_AMOUNT_PRICE":"153611.60"},{"DI_MONTH_NAME":"\u0e01\u0e23\u0e01\u0e0e\u0e32\u0e04\u0e21","TRD_QTY":"4.00","TRD_AMOUNT_PRICE":"7328.40"},{"DI_MONTH_NAME":"\u0e01\u0e23\u0e01\u0e0e\u0e32\u0e04\u0e21","TRD_QTY":"1.00","TRD_AMOUNT_PRICE":"1132.75"},{"DI_MONTH_NAME":"\u0e01\u0e23\u0e01\u0e0e\u0e32\u0e04\u0e21","TRD_QTY":"326.00","TRD_AMOUNT_PRICE":"465370.00"},{"DI_MONTH_NAME":"\u0e01\u0e23\u0e01\u0e0e\u0e32\u0e04\u0e21","TRD_QTY":"4.00","TRD_AMOUNT_PRICE":"7560.00"},{"DI_MONTH_NAME":"\u0e01\u0e23\u0e01\u0e0e\u0e32\u0e04\u0e21","TRD_QTY":"12.00","TRD_AMOUNT_PRICE":"22560.00"},{"DI_MONTH_NAME":"\u0e01\u0e23\u0e01\u0e0e\u0e32\u0e04\u0e21","TRD_QTY":"869.00","TRD_AMOUNT_PRICE":"1547781.60"},{"DI_MONTH_NAME":"\u0e01\u0e23\u0e01\u0e0e\u0e32\u0e04\u0e21","TRD_QTY":"655.00","TRD_AMOUNT_PRICE":"1099010.00"},{"DI_MONTH_NAME":"\u0e01\u0e23\u0e01\u0e0e\u0e32\u0e04\u0e21","TRD_QTY":"269.00","TRD_AMOUNT_PRICE":"443453.00"},{"DI_MONTH_NAME":"\u0e01\u0e23\u0e01\u0e0e\u0e32\u0e04\u0e21","TRD_QTY":"271.00","TRD_AMOUNT_PRICE":"577705.00"},{"DI_MONTH_NAME":"\u0e01\u0e23\u0e01\u0e0e\u0e32\u0e04\u0e21","TRD_QTY":"98.00","TRD_AMOUNT_PRICE":"155712.40"},{"DI_MONTH_NAME":"\u0e01\u0e23\u0e01\u0e0e\u0e32\u0e04\u0e21","TRD_QTY":"804.00","TRD_AMOUNT_PRICE":"1489730.00"},{"DI_MONTH_NAME":"\u0e01\u0e23\u0e01\u0e0e\u0e32\u0e04\u0e21","TRD_QTY":"3.00","TRD_AMOUNT_PRICE":"5250.00"},{"DI_MONTH_NAME":"\u0e01\u0e23\u0e01\u0e0e\u0e32\u0e04\u0e21","TRD_QTY":"46.00","TRD_AMOUNT_PRICE":"80140.00"},{"DI_MONTH_NAME":"\u0e01\u0e23\u0e01\u0e0e\u0e32\u0e04\u0e21","TRD_QTY":"21.00","TRD_AMOUNT_PRICE":"38680.00"},{"DI_MONTH_NAME":"\u0e01\u0e23\u0e01\u0e0e\u0e32\u0e04\u0e21","TRD_QTY":"8.00","TRD_AMOUNT_PRICE":"8240.00"},{"DI_MONTH_NAME":"\u0e01\u0e23\u0e01\u0e0e\u0e32\u0e04\u0e21","TRD_QTY":"31.00","TRD_AMOUNT_PRICE":"58150.00"},{"DI_MONTH_NAME":"\u0e01\u0e23\u0e01\u0e0e\u0e32\u0e04\u0e21","TRD_QTY":"14.00","TRD_AMOUNT_PRICE":"16020.00"},{"DI_MONTH_NAME":"\u0e01\u0e23\u0e01\u0e0e\u0e32\u0e04\u0e21","TRD_QTY":"100.00","TRD_AMOUNT_PRICE":"137720.00"},{"DI_MONTH_NAME":"\u0e01\u0e23\u0e01\u0e0e\u0e32\u0e04\u0e21","TRD_QTY":"18.00","TRD_AMOUNT_PRICE":"27500.00"},{"DI_MONTH_NAME":"\u0e01\u0e23\u0e01\u0e0e\u0e32\u0e04\u0e21","TRD_QTY":"29.00","TRD_AMOUNT_PRICE":"57970.00"},{"DI_MONTH_NAME":"\u0e01\u0e23\u0e01\u0e0e\u0e32\u0e04\u0e21","TRD_QTY":"93.00","TRD_AMOUNT_PRICE":"178380.00"},{"DI_MONTH_NAME":"\u0e2a\u0e34\u0e07\u0e2b\u0e32\u0e04\u0e21","TRD_QTY":"79.00","TRD_AMOUNT_PRICE":"167372.75"},{"DI_MONTH_NAME":"\u0e2a\u0e34\u0e07\u0e2b\u0e32\u0e04\u0e21","TRD_QTY":"5233.00","TRD_AMOUNT_PRICE":"7942706.90"},{"DI_MONTH_NAME":"\u0e2a\u0e34\u0e07\u0e2b\u0e32\u0e04\u0e21","TRD_QTY":"307.00","TRD_AMOUNT_PRICE":"454200.00"},{"DI_MONTH_NAME":"\u0e2a\u0e34\u0e07\u0e2b\u0e32\u0e04\u0e21","TRD_QTY":"135.00","TRD_AMOUNT_PRICE":"200090.00"},{"DI_MONTH_NAME":"\u0e2a\u0e34\u0e07\u0e2b\u0e32\u0e04\u0e21","TRD_QTY":"62.00","TRD_AMOUNT_PRICE":"90680.00"},{"DI_MONTH_NAME":"\u0e2a\u0e34\u0e07\u0e2b\u0e32\u0e04\u0e21","TRD_QTY":"80.00","TRD_AMOUNT_PRICE":"126190.00"},{"DI_MONTH_NAME":"\u0e2a\u0e34\u0e07\u0e2b\u0e32\u0e04\u0e21","TRD_QTY":"383.00","TRD_AMOUNT_PRICE":"513490.00"},{"DI_MONTH_NAME":"\u0e2a\u0e34\u0e07\u0e2b\u0e32\u0e04\u0e21","TRD_QTY":"121.00","TRD_AMOUNT_PRICE":"186660.00"},{"DI_MONTH_NAME":"\u0e2a\u0e34\u0e07\u0e2b\u0e32\u0e04\u0e21","TRD_QTY":"12.00","TRD_AMOUNT_PRICE":"19800.00"},{"DI_MONTH_NAME":"\u0e2a\u0e34\u0e07\u0e2b\u0e32\u0e04\u0e21","TRD_QTY":"4.00","TRD_AMOUNT_PRICE":"27540.60"},{"DI_MONTH_NAME":"\u0e2a\u0e34\u0e07\u0e2b\u0e32\u0e04\u0e21","TRD_QTY":"114.00","TRD_AMOUNT_PRICE":"162620.00"},{"DI_MONTH_NAME":"\u0e2a\u0e34\u0e07\u0e2b\u0e32\u0e04\u0e21","TRD_QTY":"117.00","TRD_AMOUNT_PRICE":"184942.00"},{"DI_MONTH_NAME":"\u0e2a\u0e34\u0e07\u0e2b\u0e32\u0e04\u0e21","TRD_QTY":"294.00","TRD_AMOUNT_PRICE":"520630.00"},{"DI_MONTH_NAME":"\u0e2a\u0e34\u0e07\u0e2b\u0e32\u0e04\u0e21","TRD_QTY":"2336.00","TRD_AMOUNT_PRICE":"3796890.00"},{"DI_MONTH_NAME":"\u0e2a\u0e34\u0e07\u0e2b\u0e32\u0e04\u0e21","TRD_QTY":"270.00","TRD_AMOUNT_PRICE":"575742.00"},{"DI_MONTH_NAME":"\u0e2a\u0e34\u0e07\u0e2b\u0e32\u0e04\u0e21","TRD_QTY":"1.00","TRD_AMOUNT_PRICE":"1428.25"},{"DI_MONTH_NAME":"\u0e2a\u0e34\u0e07\u0e2b\u0e32\u0e04\u0e21","TRD_QTY":"153.00","TRD_AMOUNT_PRICE":"210000.00"},{"DI_MONTH_NAME":"\u0e2a\u0e34\u0e07\u0e2b\u0e32\u0e04\u0e21","TRD_QTY":"5394.00","TRD_AMOUNT_PRICE":"8191335.90"},{"DI_MONTH_NAME":"\u0e2a\u0e34\u0e07\u0e2b\u0e32\u0e04\u0e21","TRD_QTY":"26.00","TRD_AMOUNT_PRICE":"41380.00"},{"DI_MONTH_NAME":"\u0e2a\u0e34\u0e07\u0e2b\u0e32\u0e04\u0e21","TRD_QTY":"73.00","TRD_AMOUNT_PRICE":"148830.00"},{"DI_MONTH_NAME":"\u0e2a\u0e34\u0e07\u0e2b\u0e32\u0e04\u0e21","TRD_QTY":"2262.00","TRD_AMOUNT_PRICE":"3533396.75"},{"DI_MONTH_NAME":"\u0e2a\u0e34\u0e07\u0e2b\u0e32\u0e04\u0e21","TRD_QTY":"342.00","TRD_AMOUNT_PRICE":"472600.00"},{"DI_MONTH_NAME":"\u0e2a\u0e34\u0e07\u0e2b\u0e32\u0e04\u0e21","TRD_QTY":"531.00","TRD_AMOUNT_PRICE":"826650.00"},{"DI_MONTH_NAME":"\u0e2a\u0e34\u0e07\u0e2b\u0e32\u0e04\u0e21","TRD_QTY":"45.00","TRD_AMOUNT_PRICE":"66840.00"},{"DI_MONTH_NAME":"\u0e2a\u0e34\u0e07\u0e2b\u0e32\u0e04\u0e21","TRD_QTY":"121.00","TRD_AMOUNT_PRICE":"184620.00"},{"DI_MONTH_NAME":"\u0e2a\u0e34\u0e07\u0e2b\u0e32\u0e04\u0e21","TRD_QTY":"118.00","TRD_AMOUNT_PRICE":"297240.00"},{"DI_MONTH_NAME":"\u0e2a\u0e34\u0e07\u0e2b\u0e32\u0e04\u0e21","TRD_QTY":"4.00","TRD_AMOUNT_PRICE":"5520.00"},{"DI_MONTH_NAME":"\u0e2a\u0e34\u0e07\u0e2b\u0e32\u0e04\u0e21","TRD_QTY":"109.00","TRD_AMOUNT_PRICE":"154060.00"},{"DI_MONTH_NAME":"\u0e2a\u0e34\u0e07\u0e2b\u0e32\u0e04\u0e21","TRD_QTY":"8.00","TRD_AMOUNT_PRICE":"18518.00"},{"DI_MONTH_NAME":"\u0e2a\u0e34\u0e07\u0e2b\u0e32\u0e04\u0e21","TRD_QTY":"3.00","TRD_AMOUNT_PRICE":"2866.35"},{"DI_MONTH_NAME":"\u0e2a\u0e34\u0e07\u0e2b\u0e32\u0e04\u0e21","TRD_QTY":"406.00","TRD_AMOUNT_PRICE":"628421.50"},{"DI_MONTH_NAME":"\u0e2a\u0e34\u0e07\u0e2b\u0e32\u0e04\u0e21","TRD_QTY":"4.00","TRD_AMOUNT_PRICE":"5480.00"},{"DI_MONTH_NAME":"\u0e2a\u0e34\u0e07\u0e2b\u0e32\u0e04\u0e21","TRD_QTY":"7.00","TRD_AMOUNT_PRICE":"13160.00"},{"DI_MONTH_NAME":"\u0e2a\u0e34\u0e07\u0e2b\u0e32\u0e04\u0e21","TRD_QTY":"662.00","TRD_AMOUNT_PRICE":"991207.60"},{"DI_MONTH_NAME":"\u0e2a\u0e34\u0e07\u0e2b\u0e32\u0e04\u0e21","TRD_QTY":"969.00","TRD_AMOUNT_PRICE":"1565800.00"},{"DI_MONTH_NAME":"\u0e2a\u0e34\u0e07\u0e2b\u0e32\u0e04\u0e21","TRD_QTY":"212.00","TRD_AMOUNT_PRICE":"438380.00"},{"DI_MONTH_NAME":"\u0e2a\u0e34\u0e07\u0e2b\u0e32\u0e04\u0e21","TRD_QTY":"347.00","TRD_AMOUNT_PRICE":"827290.00"},{"DI_MONTH_NAME":"\u0e2a\u0e34\u0e07\u0e2b\u0e32\u0e04\u0e21","TRD_QTY":"150.00","TRD_AMOUNT_PRICE":"238770.00"},{"DI_MONTH_NAME":"\u0e2a\u0e34\u0e07\u0e2b\u0e32\u0e04\u0e21","TRD_QTY":"806.00","TRD_AMOUNT_PRICE":"1349600.00"},{"DI_MONTH_NAME":"\u0e2a\u0e34\u0e07\u0e2b\u0e32\u0e04\u0e21","TRD_QTY":"33.00","TRD_AMOUNT_PRICE":"64890.00"},{"DI_MONTH_NAME":"\u0e2a\u0e34\u0e07\u0e2b\u0e32\u0e04\u0e21","TRD_QTY":"60.00","TRD_AMOUNT_PRICE":"84360.00"},{"DI_MONTH_NAME":"\u0e2a\u0e34\u0e07\u0e2b\u0e32\u0e04\u0e21","TRD_QTY":"44.00","TRD_AMOUNT_PRICE":"85020.00"},{"DI_MONTH_NAME":"\u0e2a\u0e34\u0e07\u0e2b\u0e32\u0e04\u0e21","TRD_QTY":"15.00","TRD_AMOUNT_PRICE":"29810.00"},{"DI_MONTH_NAME":"\u0e2a\u0e34\u0e07\u0e2b\u0e32\u0e04\u0e21","TRD_QTY":"48.00","TRD_AMOUNT_PRICE":"77676.60"},{"DI_MONTH_NAME":"\u0e2a\u0e34\u0e07\u0e2b\u0e32\u0e04\u0e21","TRD_QTY":"32.00","TRD_AMOUNT_PRICE":"68880.00"},{"DI_MONTH_NAME":"\u0e2a\u0e34\u0e07\u0e2b\u0e32\u0e04\u0e21","TRD_QTY":"81.00","TRD_AMOUNT_PRICE":"151020.00"},{"DI_MONTH_NAME":"\u0e2a\u0e34\u0e07\u0e2b\u0e32\u0e04\u0e21","TRD_QTY":"32.00","TRD_AMOUNT_PRICE":"49500.00"},{"DI_MONTH_NAME":"\u0e2a\u0e34\u0e07\u0e2b\u0e32\u0e04\u0e21","TRD_QTY":"12.00","TRD_AMOUNT_PRICE":"18000.00"},{"DI_MONTH_NAME":"\u0e01\u0e31\u0e19\u0e22\u0e32\u0e22\u0e19","TRD_QTY":"6.00","TRD_AMOUNT_PRICE":"18900.00"},{"DI_MONTH_NAME":"\u0e01\u0e31\u0e19\u0e22\u0e32\u0e22\u0e19","TRD_QTY":"88.00","TRD_AMOUNT_PRICE":"223006.50"},{"DI_MONTH_NAME":"\u0e01\u0e31\u0e19\u0e22\u0e32\u0e22\u0e19","TRD_QTY":"3320.00","TRD_AMOUNT_PRICE":"5041516.10"},{"DI_MONTH_NAME":"\u0e01\u0e31\u0e19\u0e22\u0e32\u0e22\u0e19","TRD_QTY":"248.00","TRD_AMOUNT_PRICE":"427750.00"},{"DI_MONTH_NAME":"\u0e01\u0e31\u0e19\u0e22\u0e32\u0e22\u0e19","TRD_QTY":"207.00","TRD_AMOUNT_PRICE":"283950.00"},{"DI_MONTH_NAME":"\u0e01\u0e31\u0e19\u0e22\u0e32\u0e22\u0e19","TRD_QTY":"4.00","TRD_AMOUNT_PRICE":"7328.40"},{"DI_MONTH_NAME":"\u0e01\u0e31\u0e19\u0e22\u0e32\u0e22\u0e19","TRD_QTY":"96.00","TRD_AMOUNT_PRICE":"167110.00"},{"DI_MONTH_NAME":"\u0e01\u0e31\u0e19\u0e22\u0e32\u0e22\u0e19","TRD_QTY":"91.00","TRD_AMOUNT_PRICE":"144570.00"},{"DI_MONTH_NAME":"\u0e01\u0e31\u0e19\u0e22\u0e32\u0e22\u0e19","TRD_QTY":"395.00","TRD_AMOUNT_PRICE":"584560.00"},{"DI_MONTH_NAME":"\u0e01\u0e31\u0e19\u0e22\u0e32\u0e22\u0e19","TRD_QTY":"88.00","TRD_AMOUNT_PRICE":"141010.00"},{"DI_MONTH_NAME":"\u0e01\u0e31\u0e19\u0e22\u0e32\u0e22\u0e19","TRD_QTY":"1.00","TRD_AMOUNT_PRICE":"1350.00"},{"DI_MONTH_NAME":"\u0e01\u0e31\u0e19\u0e22\u0e32\u0e22\u0e19","TRD_QTY":"1.00","TRD_AMOUNT_PRICE":"1224.00"},{"DI_MONTH_NAME":"\u0e01\u0e31\u0e19\u0e22\u0e32\u0e22\u0e19","TRD_QTY":"16.00","TRD_AMOUNT_PRICE":"27140.00"},{"DI_MONTH_NAME":"\u0e01\u0e31\u0e19\u0e22\u0e32\u0e22\u0e19","TRD_QTY":"88.00","TRD_AMOUNT_PRICE":"153620.30"},{"DI_MONTH_NAME":"\u0e01\u0e31\u0e19\u0e22\u0e32\u0e22\u0e19","TRD_QTY":"262.00","TRD_AMOUNT_PRICE":"516140.00"},{"DI_MONTH_NAME":"\u0e01\u0e31\u0e19\u0e22\u0e32\u0e22\u0e19","TRD_QTY":"1906.00","TRD_AMOUNT_PRICE":"2889832.00"},{"DI_MONTH_NAME":"\u0e01\u0e31\u0e19\u0e22\u0e32\u0e22\u0e19","TRD_QTY":"200.00","TRD_AMOUNT_PRICE":"390355.00"},{"DI_MONTH_NAME":"\u0e01\u0e31\u0e19\u0e22\u0e32\u0e22\u0e19","TRD_QTY":"168.00","TRD_AMOUNT_PRICE":"246450.00"},{"DI_MONTH_NAME":"\u0e01\u0e31\u0e19\u0e22\u0e32\u0e22\u0e19","TRD_QTY":"5484.00","TRD_AMOUNT_PRICE":"8489183.15"},{"DI_MONTH_NAME":"\u0e01\u0e31\u0e19\u0e22\u0e32\u0e22\u0e19","TRD_QTY":"11.00","TRD_AMOUNT_PRICE":"18470.00"},{"DI_MONTH_NAME":"\u0e01\u0e31\u0e19\u0e22\u0e32\u0e22\u0e19","TRD_QTY":"22.00","TRD_AMOUNT_PRICE":"38480.00"},{"DI_MONTH_NAME":"\u0e01\u0e31\u0e19\u0e22\u0e32\u0e22\u0e19","TRD_QTY":"24.00","TRD_AMOUNT_PRICE":"48460.00"},{"DI_MONTH_NAME":"\u0e01\u0e31\u0e19\u0e22\u0e32\u0e22\u0e19","TRD_QTY":"1952.00","TRD_AMOUNT_PRICE":"2864105.00"},{"DI_MONTH_NAME":"\u0e01\u0e31\u0e19\u0e22\u0e32\u0e22\u0e19","TRD_QTY":"323.00","TRD_AMOUNT_PRICE":"430240.00"},{"DI_MONTH_NAME":"\u0e01\u0e31\u0e19\u0e22\u0e32\u0e22\u0e19","TRD_QTY":"664.00","TRD_AMOUNT_PRICE":"948208.50"},{"DI_MONTH_NAME":"\u0e01\u0e31\u0e19\u0e22\u0e32\u0e22\u0e19","TRD_QTY":"39.00","TRD_AMOUNT_PRICE":"69390.00"},{"DI_MONTH_NAME":"\u0e01\u0e31\u0e19\u0e22\u0e32\u0e22\u0e19","TRD_QTY":"133.00","TRD_AMOUNT_PRICE":"210100.00"},{"DI_MONTH_NAME":"\u0e01\u0e31\u0e19\u0e22\u0e32\u0e22\u0e19","TRD_QTY":"52.00","TRD_AMOUNT_PRICE":"91000.00"},{"DI_MONTH_NAME":"\u0e01\u0e31\u0e19\u0e22\u0e32\u0e22\u0e19","TRD_QTY":"12.00","TRD_AMOUNT_PRICE":"16560.00"},{"DI_MONTH_NAME":"\u0e01\u0e31\u0e19\u0e22\u0e32\u0e22\u0e19","TRD_QTY":"64.00","TRD_AMOUNT_PRICE":"105320.00"},{"DI_MONTH_NAME":"\u0e01\u0e31\u0e19\u0e22\u0e32\u0e22\u0e19","TRD_QTY":"326.00","TRD_AMOUNT_PRICE":"545790.00"},{"DI_MONTH_NAME":"\u0e01\u0e31\u0e19\u0e22\u0e32\u0e22\u0e19","TRD_QTY":"4.00","TRD_AMOUNT_PRICE":"5480.00"},{"DI_MONTH_NAME":"\u0e01\u0e31\u0e19\u0e22\u0e32\u0e22\u0e19","TRD_QTY":"870.00","TRD_AMOUNT_PRICE":"1329160.30"},{"DI_MONTH_NAME":"\u0e01\u0e31\u0e19\u0e22\u0e32\u0e22\u0e19","TRD_QTY":"469.00","TRD_AMOUNT_PRICE":"877030.00"},{"DI_MONTH_NAME":"\u0e01\u0e31\u0e19\u0e22\u0e32\u0e22\u0e19","TRD_QTY":"256.00","TRD_AMOUNT_PRICE":"452830.00"},{"DI_MONTH_NAME":"\u0e01\u0e31\u0e19\u0e22\u0e32\u0e22\u0e19","TRD_QTY":"375.00","TRD_AMOUNT_PRICE":"936630.00"},{"DI_MONTH_NAME":"\u0e01\u0e31\u0e19\u0e22\u0e32\u0e22\u0e19","TRD_QTY":"146.00","TRD_AMOUNT_PRICE":"243209.00"},{"DI_MONTH_NAME":"\u0e01\u0e31\u0e19\u0e22\u0e32\u0e22\u0e19","TRD_QTY":"851.00","TRD_AMOUNT_PRICE":"1526350.00"},{"DI_MONTH_NAME":"\u0e01\u0e31\u0e19\u0e22\u0e32\u0e22\u0e19","TRD_QTY":"28.00","TRD_AMOUNT_PRICE":"46540.00"},{"DI_MONTH_NAME":"\u0e01\u0e31\u0e19\u0e22\u0e32\u0e22\u0e19","TRD_QTY":"35.00","TRD_AMOUNT_PRICE":"68690.00"},{"DI_MONTH_NAME":"\u0e01\u0e31\u0e19\u0e22\u0e32\u0e22\u0e19","TRD_QTY":"44.00","TRD_AMOUNT_PRICE":"58560.00"},{"DI_MONTH_NAME":"\u0e01\u0e31\u0e19\u0e22\u0e32\u0e22\u0e19","TRD_QTY":"91.00","TRD_AMOUNT_PRICE":"170000.00"},{"DI_MONTH_NAME":"\u0e15\u0e38\u0e25\u0e32\u0e04\u0e21","TRD_QTY":"47.00","TRD_AMOUNT_PRICE":"134980.00"},{"DI_MONTH_NAME":"\u0e15\u0e38\u0e25\u0e32\u0e04\u0e21","TRD_QTY":"2341.00","TRD_AMOUNT_PRICE":"3430344.82"},{"DI_MONTH_NAME":"\u0e15\u0e38\u0e25\u0e32\u0e04\u0e21","TRD_QTY":"56.00","TRD_AMOUNT_PRICE":"101600.00"},{"DI_MONTH_NAME":"\u0e15\u0e38\u0e25\u0e32\u0e04\u0e21","TRD_QTY":"210.00","TRD_AMOUNT_PRICE":"313990.00"},{"DI_MONTH_NAME":"\u0e15\u0e38\u0e25\u0e32\u0e04\u0e21","TRD_QTY":"34.00","TRD_AMOUNT_PRICE":"57300.00"},{"DI_MONTH_NAME":"\u0e15\u0e38\u0e25\u0e32\u0e04\u0e21","TRD_QTY":"109.00","TRD_AMOUNT_PRICE":"149304.25"},{"DI_MONTH_NAME":"\u0e15\u0e38\u0e25\u0e32\u0e04\u0e21","TRD_QTY":"295.00","TRD_AMOUNT_PRICE":"390180.00"},{"DI_MONTH_NAME":"\u0e15\u0e38\u0e25\u0e32\u0e04\u0e21","TRD_QTY":"59.00","TRD_AMOUNT_PRICE":"95810.00"},{"DI_MONTH_NAME":"\u0e15\u0e38\u0e25\u0e32\u0e04\u0e21","TRD_QTY":"8.00","TRD_AMOUNT_PRICE":"24680.00"},{"DI_MONTH_NAME":"\u0e15\u0e38\u0e25\u0e32\u0e04\u0e21","TRD_QTY":"206.00","TRD_AMOUNT_PRICE":"137960.00"},{"DI_MONTH_NAME":"\u0e15\u0e38\u0e25\u0e32\u0e04\u0e21","TRD_QTY":"95.00","TRD_AMOUNT_PRICE":"158980.00"},{"DI_MONTH_NAME":"\u0e15\u0e38\u0e25\u0e32\u0e04\u0e21","TRD_QTY":"175.00","TRD_AMOUNT_PRICE":"298700.00"},{"DI_MONTH_NAME":"\u0e15\u0e38\u0e25\u0e32\u0e04\u0e21","TRD_QTY":"1166.00","TRD_AMOUNT_PRICE":"1874760.00"},{"DI_MONTH_NAME":"\u0e15\u0e38\u0e25\u0e32\u0e04\u0e21","TRD_QTY":"205.00","TRD_AMOUNT_PRICE":"287070.00"},{"DI_MONTH_NAME":"\u0e15\u0e38\u0e25\u0e32\u0e04\u0e21","TRD_QTY":"110.00","TRD_AMOUNT_PRICE":"144660.00"},{"DI_MONTH_NAME":"\u0e15\u0e38\u0e25\u0e32\u0e04\u0e21","TRD_QTY":"4409.00","TRD_AMOUNT_PRICE":"6628053.85"},{"DI_MONTH_NAME":"\u0e15\u0e38\u0e25\u0e32\u0e04\u0e21","TRD_QTY":"1.00","TRD_AMOUNT_PRICE":"2970.00"},{"DI_MONTH_NAME":"\u0e15\u0e38\u0e25\u0e32\u0e04\u0e21","TRD_QTY":"79.00","TRD_AMOUNT_PRICE":"146670.00"},{"DI_MONTH_NAME":"\u0e15\u0e38\u0e25\u0e32\u0e04\u0e21","TRD_QTY":"1309.00","TRD_AMOUNT_PRICE":"2055870.00"},{"DI_MONTH_NAME":"\u0e15\u0e38\u0e25\u0e32\u0e04\u0e21","TRD_QTY":"292.00","TRD_AMOUNT_PRICE":"408770.00"},{"DI_MONTH_NAME":"\u0e15\u0e38\u0e25\u0e32\u0e04\u0e21","TRD_QTY":"438.00","TRD_AMOUNT_PRICE":"793900.00"},{"DI_MONTH_NAME":"\u0e15\u0e38\u0e25\u0e32\u0e04\u0e21","TRD_QTY":"3.00","TRD_AMOUNT_PRICE":"3660.00"},{"DI_MONTH_NAME":"\u0e15\u0e38\u0e25\u0e32\u0e04\u0e21","TRD_QTY":"138.00","TRD_AMOUNT_PRICE":"212020.00"},{"DI_MONTH_NAME":"\u0e15\u0e38\u0e25\u0e32\u0e04\u0e21","TRD_QTY":"39.00","TRD_AMOUNT_PRICE":"58500.00"},{"DI_MONTH_NAME":"\u0e15\u0e38\u0e25\u0e32\u0e04\u0e21","TRD_QTY":"12.00","TRD_AMOUNT_PRICE":"15960.00"},{"DI_MONTH_NAME":"\u0e15\u0e38\u0e25\u0e32\u0e04\u0e21","TRD_QTY":"74.00","TRD_AMOUNT_PRICE":"112240.00"},{"DI_MONTH_NAME":"\u0e15\u0e38\u0e25\u0e32\u0e04\u0e21","TRD_QTY":"212.00","TRD_AMOUNT_PRICE":"311910.00"},{"DI_MONTH_NAME":"\u0e15\u0e38\u0e25\u0e32\u0e04\u0e21","TRD_QTY":"4.00","TRD_AMOUNT_PRICE":"7740.00"},{"DI_MONTH_NAME":"\u0e15\u0e38\u0e25\u0e32\u0e04\u0e21","TRD_QTY":"387.00","TRD_AMOUNT_PRICE":"629695.80"},{"DI_MONTH_NAME":"\u0e15\u0e38\u0e25\u0e32\u0e04\u0e21","TRD_QTY":"418.00","TRD_AMOUNT_PRICE":"656110.00"},{"DI_MONTH_NAME":"\u0e15\u0e38\u0e25\u0e32\u0e04\u0e21","TRD_QTY":"185.00","TRD_AMOUNT_PRICE":"316530.00"},{"DI_MONTH_NAME":"\u0e15\u0e38\u0e25\u0e32\u0e04\u0e21","TRD_QTY":"225.00","TRD_AMOUNT_PRICE":"505340.00"},{"DI_MONTH_NAME":"\u0e15\u0e38\u0e25\u0e32\u0e04\u0e21","TRD_QTY":"54.00","TRD_AMOUNT_PRICE":"80780.00"},{"DI_MONTH_NAME":"\u0e15\u0e38\u0e25\u0e32\u0e04\u0e21","TRD_QTY":"462.00","TRD_AMOUNT_PRICE":"734230.00"},{"DI_MONTH_NAME":"\u0e15\u0e38\u0e25\u0e32\u0e04\u0e21","TRD_QTY":"6.00","TRD_AMOUNT_PRICE":"13100.00"},{"DI_MONTH_NAME":"\u0e15\u0e38\u0e25\u0e32\u0e04\u0e21","TRD_QTY":"39.00","TRD_AMOUNT_PRICE":"59940.00"},{"DI_MONTH_NAME":"\u0e15\u0e38\u0e25\u0e32\u0e04\u0e21","TRD_QTY":"32.00","TRD_AMOUNT_PRICE":"50320.00"},{"DI_MONTH_NAME":"\u0e15\u0e38\u0e25\u0e32\u0e04\u0e21","TRD_QTY":"16.00","TRD_AMOUNT_PRICE":"22240.00"},{"DI_MONTH_NAME":"\u0e15\u0e38\u0e25\u0e32\u0e04\u0e21","TRD_QTY":"31.00","TRD_AMOUNT_PRICE":"44050.00"},{"DI_MONTH_NAME":"\u0e15\u0e38\u0e25\u0e32\u0e04\u0e21","TRD_QTY":"5.00","TRD_AMOUNT_PRICE":"10574.20"},{"DI_MONTH_NAME":"\u0e15\u0e38\u0e25\u0e32\u0e04\u0e21","TRD_QTY":"20.00","TRD_AMOUNT_PRICE":"39900.00"}]